snake/__init__.py
snake/board.py
snake/broadcaster.py
snake/cli.py
snake/engine.py
snake/food.py
snake/game.py
snake/keyb.py
snake/snaky.py
snake/util.py
snake_terminal_pp-0.2.2.dist-info/AUTHORS.rst
snake_terminal_pp-0.2.2.dist-info/LICENSE
snake_terminal_pp-0.2.2.dist-info/METADATA
snake_terminal_pp-0.2.2.dist-info/WHEEL
snake_terminal_pp-0.2.2.dist-info/entry_points.txt
snake_terminal_pp-0.2.2.dist-info/top_level.txt
snake_terminal_pp-0.2.2.dist-info/RECORD
