Metadata-Version: 2.1
Name: snake-terminal-pp
Version: 0.2.2
Summary: A simple snake game on terminal.
Home-page: https://github.com/lparolari/snake
Author: Luca Parolari
Author-email: luca.parolari23@gmail.com
License: MIT license
Keywords: snake
Platform: UNKNOWN
Classifier: Development Status :: 2 - Pre-Alpha
Classifier: Intended Audience :: Developers
Classifier: License :: OSI Approved :: MIT License
Classifier: Natural Language :: English
Classifier: Programming Language :: Python :: 3.6
Classifier: Programming Language :: Python :: 3.7
Requires-Python: >=2.7, !=3.0.*, !=3.1.*, !=3.2.*, !=3.3.*, !=3.4.*
Requires-Dist: Click (>=6.0)
Requires-Dist: numpy
Requires-Dist: keyboard
Requires-Dist: pynput
Requires-Dist: asciimatics
